genxword/__init__.py
genxword/calculate.py
genxword/cli.py
genxword/complexstring.py
genxword/complexstring2.py
genxword/control.py
genxword/gui.py
genxword/data/gumby.lang
genxword/data/help_page
genxword-2.2.0.data/data/share/applications/genxword-gtk.desktop
genxword-2.2.0.data/data/share/locale/ca/LC_MESSAGES/genxword.mo
genxword-2.2.0.data/data/share/locale/de/LC_MESSAGES/genxword.mo
genxword-2.2.0.data/data/share/locale/es/LC_MESSAGES/genxword.mo
genxword-2.2.0.data/data/share/locale/fr/LC_MESSAGES/genxword.mo
genxword-2.2.0.data/data/share/locale/gl/LC_MESSAGES/genxword.mo
genxword-2.2.0.data/data/share/locale/nl/LC_MESSAGES/genxword.mo
genxword-2.2.0.data/data/share/locale/th/LC_MESSAGES/genxword.mo
genxword-2.2.0.data/data/share/pixmaps/genxword-gtk.png
genxword-2.2.0.dist-info/LICENSE
genxword-2.2.0.dist-info/METADATA
genxword-2.2.0.dist-info/WHEEL
genxword-2.2.0.dist-info/entry_points.txt
genxword-2.2.0.dist-info/top_level.txt
genxword-2.2.0.dist-info/RECORD
