Metadata-Version: 2.1
Name: genxword
Version: 2.2.0
Summary: A crossword generator
Home-page: https://github.com/riverrun/genxword
Author: David Whitlock
Author-email: alovedalongthe@gmail.com
License: GPLv3
Platform: any
Classifier: Development Status :: 5 - Production/Stable
Classifier: Environment :: Console
Classifier: Environment :: X11 Applications :: GTK
Classifier: Intended Audience :: End Users/Desktop
Classifier: Intended Audience :: Developers
Classifier: Intended Audience :: Education
Classifier: License :: OSI Approved :: GNU General Public License v3 (GPLv3)
Classifier: Operating System :: OS Independent
Classifier: Programming Language :: Python
Classifier: Programming Language :: Python :: 3
Classifier: Topic :: Education
Classifier: Topic :: Office/Business
License-File: LICENSE
Requires-Dist: pycairo
Requires-Dist: PyGObject
Provides-Extra: dev
Requires-Dist: pytest ; extra == 'dev'
Requires-Dist: ipuz ; extra == 'dev'
